simpleoptics/__init__.py
simpleoptics/waveguide.py
simpleoptics/devices/__init__.py
simpleoptics/devices/resonators.py
simpleoptics/devices/rings.py
simpleoptics/epsilon_data/__init__.py
simpleoptics/epsilon_data/formulas.py
simpleoptics/helpers/__init__.py
simpleoptics/helpers/preambule.py
simpleoptics/helpers/waveforms.py
simpleoptics/simulators/__init__.py
simpleoptics/simulators/goell.py
simpleoptics/simulators/planar.py
simpleoptics/simulators/rectangular.py
simple_guided_optics_letishnick-2020.10.8.dev0.dist-info/LICENSE.txt
simple_guided_optics_letishnick-2020.10.8.dev0.dist-info/METADATA
simple_guided_optics_letishnick-2020.10.8.dev0.dist-info/WHEEL
simple_guided_optics_letishnick-2020.10.8.dev0.dist-info/top_level.txt
simple_guided_optics_letishnick-2020.10.8.dev0.dist-info/RECORD
