Metadata-Version: 2.1
Name: simple-guided-optics-letishnick
Version: 2020.10.8.dev0
Summary: A package that provides several classic calculation methods for guided optics
Home-page: https://github.com/pypa/sampleproject
Author: Nick Cheplagin
Author-email: letishnick@gmail.com
License: UNKNOWN
Platform: UNKNOWN
Classifier: Programming Language :: Python :: 3
Classifier: License :: OSI Approved :: GNU General Public License v3 (GPLv3)
Classifier: Operating System :: OS Independent
Requires-Python: >=3.6
